{"index.md":"7020d8df","src_web-engineering-testing.md":"87d64944","demo_webpack_index.md":"3dd553e9","readme.md":"a7c3e456","src_web-product.md":"b27d4769","demo_nodejs-cli_index.md":"b7efb98d","demo_antv-g6_index.md":"acbedafb","demo_pnpm_index.md":"71c26181","src_web-engineering-standard.md":"517628b9","demo_design-patterns_index.md":"b7febdcf","demo_canvas_index.md":"b19d61e3","src_web-engineering.md":"8a8c5ecd","src_web-data-visualization.md":"cc6f6f43","demo_sandpack_readme.md":"a22496ba","demo_test-jest_index.md":"efa8881b","demo_nodejs_index.md":"95665957","demo_ts_index.md":"4ef428f0","demo_react_index.md":"dbbb619e"}
